setup.cfg
setup.py
fast_sparCC.egg-info/PKG-INFO
fast_sparCC.egg-info/SOURCES.txt
fast_sparCC.egg-info/dependency_links.txt
fast_sparCC.egg-info/pbr.json
fast_sparCC.egg-info/requires.txt
fast_sparCC.egg-info/top_level.txt
scripts/fast_sparCC.py
sparcc_fast/__init__.py
sparcc_fast/bootstrap_correlations.py
sparcc_fast/run_sparcc.py
sparcc_fast/sparcc_functions.py
sparcc_fast/utils.py