Metadata-Version: 1.1
Name: fast-sparCC
Version: 0.1.5
Summary: A fast command line interface to find correlations in biom tables with SparCC.
Home-page: https://github.com/shafferm/fast_sparCC
Author: Michael Shaffer
Author-email: michael.shaffer@ucdenver.edu
License: BSD
Download-URL: https://github.com/shafferm/fast_sparCC/archive/v0.1.5.tar.gz
Platform: UNKNOWN
